vmdcube/__init__.py
vmdcube/materials.py
vmdcube/scripts.py
vmdcube/utils.py
vmdcube/vmdcube.py
vmdcube-1.0.5.dist-info/licenses/LICENSE
vmdcube-1.0.5.dist-info/METADATA
vmdcube-1.0.5.dist-info/WHEEL
vmdcube-1.0.5.dist-info/top_level.txt
vmdcube-1.0.5.dist-info/RECORD
