Metadata-Version: 2.4
Name: VMDCube
Version: 1.0.5
Summary: A Python package for rendering cube files with VMD.
Author: Francesco Evangelista
Project-URL: Homepage, https://github.com/fevangelista/vmdcube
Project-URL: Repository, https://github.com/fevangelista/vmdcube.git
Project-URL: Issue-Tracker, https://github.com/fevangelista/vmdcube/issues
Keywords: vmd,cube,rendering
Classifier: License :: OSI Approved :: BSD License
Requires-Python: >=3.8
License-File: LICENSE
Requires-Dist: numpy>=1.19
Requires-Dist: matplotlib>=3.4
Provides-Extra: test
Requires-Dist: pytest>=7.0; extra == "test"
Requires-Dist: pytest-cov>=3.0; extra == "test"
Dynamic: license-file
